{
	"1": {"Id":1,"Name":"Leo Skin 1","Dictionary":"hstattoos_overlays","MaleHash":"MP_Hstattoos_Tattoo_035_M","FemaleHash":"","Slots":[10],"Price":7500,"Donate":0},
	"2": {"Id":2,"Name":"Leo Skin 2","Dictionary":"hstattoos_overlays","MaleHash":"MP_Hstattoos_Tattoo_036_M","FemaleHash":"","Slots":[11],"Price":7500,"Donate":0},
	"3": {"Id":3,"Name":"Dragon Lore","Dictionary":"hstattoos_overlays","MaleHash":"MP_Hstattoos_Tattoo_038_M","FemaleHash":"","Slots":[2],"Price":7500,"Donate":0},
	"4": {"Id":4,"Name":"Feather of the Phoenix","Dictionary":"hstattoos_overlays","MaleHash":"MP_Hstattoos_Tattoo_039_M","FemaleHash":"MP_Hstattoos_Tattoo_039_F","Slots":[3],"Price":7500,"Donate":0},
	"5": {"Id":5,"Name":"Five Stars","Dictionary":"mpheist3_overlays","MaleHash":"mpHeist3_Tat_000_M","FemaleHash":"mpHeist3_Tat_000_F","Slots":[6],"Price":1500,"Donate":0},
	"6": {"Id":6,"Name":"Ace of Spades","Dictionary":"mpheist3_overlays","MaleHash":"mpHeist3_Tat_001_M","FemaleHash":"mpHeist3_Tat_001_F","Slots":[5],"Price":1500,"Donate":0},
	"7": {"Id":7,"Name":"Animal","Dictionary":"mpheist3_overlays","MaleHash":"mpHeist3_Tat_002_M","FemaleHash":"mpHeist3_Tat_002_F","Slots":[0],"Price":1500,"Donate":0},
	"8": {"Id":8,"Name":"Assault Rifle","Dictionary":"mpheist3_overlays","MaleHash":"mpHeist3_Tat_003_M","FemaleHash":"mpHeist3_Tat_003_F","Slots":[6],"Price":1500,"Donate":0},
	"9": {"Id":9,"Name":"Bandage","Dictionary":"mpheist3_overlays","MaleHash":"mpHeist3_Tat_004_M","FemaleHash":"mpHeist3_Tat_004_F","Slots":[7],"Price":1500,"Donate":0},
	"10": {"Id":10,"Name":"Spades","Dictionary":"mpheist3_overlays","MaleHash":"mpHeist3_Tat_005_M","FemaleHash":"mpHeist3_Tat_005_F","Slots":[5],"Price":1500,"Donate":0},
	"11": {"Id":11,"Name":"Crowned","Dictionary":"mpheist3_overlays","MaleHash":"mpHeist3_Tat_006_M","FemaleHash":"mpHeist3_Tat_006_F","Slots":[8],"Price":1500,"Donate":0},
	"12": {"Id":12,"Name":"Two Horns","Dictionary":"mpheist3_overlays","MaleHash":"mpHeist3_Tat_007_M","FemaleHash":"mpHeist3_Tat_007_F","Slots":[7,8],"Price":1500,"Donate":0},
	"13": {"Id":13,"Name":"Ice Cream","Dictionary":"mpheist3_overlays","MaleHash":"mpHeist3_Tat_008_M","FemaleHash":"mpHeist3_Tat_008_F","Slots":[2],"Price":1500,"Donate":0},
	"14": {"Id":14,"Name":"Knifed","Dictionary":"mpheist3_overlays","MaleHash":"mpHeist3_Tat_009_M","FemaleHash":"mpHeist3_Tat_009_F","Slots":[4],"Price":1500,"Donate":0},
	"15": {"Id":15,"Name":"Green Leaf","Dictionary":"mpheist3_overlays","MaleHash":"mpHeist3_Tat_010_M","FemaleHash":"mpHeist3_Tat_010_F","Slots":[4],"Price":1500,"Donate":0},
	"16": {"Id":16,"Name":"Lipstick Kiss","Dictionary":"mpheist3_overlays","MaleHash":"mpHeist3_Tat_011_M","FemaleHash":"mpHeist3_Tat_011_F","Slots":[4],"Price":1500,"Donate":0},
	"17": {"Id":17,"Name":"Razor Pop","Dictionary":"mpheist3_overlays","MaleHash":"mpHeist3_Tat_012_M","FemaleHash":"mpHeist3_Tat_012_F","Slots":[4],"Price":1500,"Donate":0},
	"18": {"Id":18,"Name":"LS Star","Dictionary":"mpheist3_overlays","MaleHash":"mpHeist3_Tat_013_M","FemaleHash":"mpHeist3_Tat_013_F","Slots":[7],"Price":1500,"Donate":0},
	"19": {"Id":19,"Name":"LS Wings","Dictionary":"mpheist3_overlays","MaleHash":"mpHeist3_Tat_014_M","FemaleHash":"mpHeist3_Tat_014_F","Slots":[0],"Price":1500,"Donate":0},
	"20": {"Id":20,"Name":"On/Off","Dictionary":"mpheist3_overlays","MaleHash":"mpHeist3_Tat_015_M","FemaleHash":"mpHeist3_Tat_015_F","Slots":[7],"Price":1500,"Donate":0},
	"21": {"Id":21,"Name":"Sleepy","Dictionary":"mpheist3_overlays","MaleHash":"mpHeist3_Tat_016_M","FemaleHash":"mpHeist3_Tat_016_F","Slots":[6],"Price":1500,"Donate":0},
	"22": {"Id":22,"Name":"Space Monkey","Dictionary":"mpheist3_overlays","MaleHash":"mpHeist3_Tat_017_M","FemaleHash":"mpHeist3_Tat_017_F","Slots":[1],"Price":1500,"Donate":0},
	"23": {"Id":23,"Name":"Stitches","Dictionary":"mpheist3_overlays","MaleHash":"mpHeist3_Tat_018_M","FemaleHash":"mpHeist3_Tat_018_F","Slots":[9],"Price":1500,"Donate":0},
	"24": {"Id":24,"Name":"Teddy Bear","Dictionary":"mpheist3_overlays","MaleHash":"mpHeist3_Tat_019_M","FemaleHash":"mpHeist3_Tat_019_F","Slots":[2],"Price":1500,"Donate":0},
	"25": {"Id":25,"Name":"UFO","Dictionary":"mpheist3_overlays","MaleHash":"mpHeist3_Tat_020_M","FemaleHash":"mpHeist3_Tat_020_F","Slots":[4],"Price":1500,"Donate":0},
	"26": {"Id":26,"Name":"Wanted","Dictionary":"mpheist3_overlays","MaleHash":"mpHeist3_Tat_021_M","FemaleHash":"mpHeist3_Tat_021_F","Slots":[7],"Price":1500,"Donate":0},
	"27": {"Id":27,"Name":"Thog's Sword","Dictionary":"mpheist3_overlays","MaleHash":"mpHeist3_Tat_022_M","FemaleHash":"mpHeist3_Tat_022_F","Slots":[6],"Price":1500,"Donate":0},
	"28": {"Id":28,"Name":"Hearts","Dictionary":"mpheist3_overlays","MaleHash":"mpHeist3_Tat_042_M","FemaleHash":"mpHeist3_Tat_042_F","Slots":[4],"Price":1500,"Donate":0},
	"29": {"Id":29,"Name":"Diamonds","Dictionary":"mpheist3_overlays","MaleHash":"mpHeist3_Tat_043_M","FemaleHash":"mpHeist3_Tat_043_F","Slots":[4],"Price":1500,"Donate":0},
	"30": {"Id":30,"Name":"Clubs","Dictionary":"mpheist3_overlays","MaleHash":"mpHeist3_Tat_044_M","FemaleHash":"mpHeist3_Tat_044_F","Slots":[4],"Price":1500,"Donate":0},
	"31": {"Id":31,"Name":"Cash is King","Dictionary":"mpbusiness_overlays","MaleHash":"MP_Buis_M_Neck_000","FemaleHash":"","Slots":[0],"Price":2500,"Donate":0},
	"32": {"Id":32,"Name":"Bold Dollar Sign","Dictionary":"mpbusiness_overlays","MaleHash":"MP_Buis_M_Neck_001","FemaleHash":"","Slots":[1],"Price":2500,"Donate":0},
	"33": {"Id":33,"Name":"Script Dollar Sign","Dictionary":"mpbusiness_overlays","MaleHash":"MP_Buis_M_Neck_002","FemaleHash":"","Slots":[2],"Price":2500,"Donate":0},
	"34": {"Id":34,"Name":"$100","Dictionary":"mpbusiness_overlays","MaleHash":"MP_Buis_M_Neck_003","FemaleHash":"","Slots":[3],"Price":2500,"Donate":0},
	"35": {"Id":35,"Name":"Val-de-Grace Logo","Dictionary":"mpbusiness_overlays","MaleHash":"","FemaleHash":"MP_Buis_F_Neck_000","Slots":[1],"Price":2500,"Donate":0},
	"36": {"Id":36,"Name":"Money Rose","Dictionary":"mpbusiness_overlays","MaleHash":"","FemaleHash":"MP_Buis_F_Neck_001","Slots":[2],"Price":2500,"Donate":0},
	"37": {"Id":37,"Name":"Los Muertos","Dictionary":"mpchristmas2_overlays","MaleHash":"MP_Xmas2_M_Tat_007","FemaleHash":"MP_Xmas2_F_Tat_007","Slots":[2],"Price":2500,"Donate":0},
	"38": {"Id":38,"Name":"Snake Head Outline","Dictionary":"mpchristmas2_overlays","MaleHash":"MP_Xmas2_M_Tat_024","FemaleHash":"MP_Xmas2_F_Tat_024","Slots":[1],"Price":2500,"Donate":0},
	"39": {"Id":39,"Name":"Snake Head Color","Dictionary":"mpchristmas2_overlays","MaleHash":"MP_Xmas2_M_Tat_025","FemaleHash":"MP_Xmas2_F_Tat_025","Slots":[1],"Price":2500,"Donate":0},
	"40": {"Id":40,"Name":"Beautiful Death","Dictionary":"mpchristmas2_overlays","MaleHash":"MP_Xmas2_M_Tat_029","FemaleHash":"MP_Xmas2_F_Tat_029","Slots":[2],"Price":2500,"Donate":0},
	"41": {"Id":41,"Name":"Lock & Load","Dictionary":"mpgunrunning_overlays","MaleHash":"MP_Gunrunning_Tattoo_003_M","FemaleHash":"MP_Gunrunning_Tattoo_003_F","Slots":[1],"Price":2500,"Donate":0},
	"42": {"Id":42,"Name":"Beautiful Eye","Dictionary":"mphipster_overlays","MaleHash":"FM_Hip_M_Tat_005","FemaleHash":"FM_Hip_F_Tat_005","Slots":[2],"Price":1750,"Donate":0},
	"43": {"Id":43,"Name":"Geo Fox","Dictionary":"mphipster_overlays","MaleHash":"FM_Hip_M_Tat_021","FemaleHash":"FM_Hip_F_Tat_021","Slots":[1],"Price":1750,"Donate":0},
	"44": {"Id":44,"Name":"Morbid Arachnid","Dictionary":"mpbiker_overlays","MaleHash":"MP_MP_Biker_Tat_009_M","FemaleHash":"MP_MP_Biker_Tat_009_F","Slots":[5],"Price":1750,"Donate":0},
	"45": {"Id":45,"Name":"FTW","Dictionary":"mpbiker_overlays","MaleHash":"MP_MP_Biker_Tat_038_M","FemaleHash":"MP_MP_Biker_Tat_038_F","Slots":[2],"Price":1750,"Donate":0},
	"46": {"Id":46,"Name":"Western Stylized","Dictionary":"mpbiker_overlays","MaleHash":"MP_MP_Biker_Tat_051_M","FemaleHash":"MP_MP_Biker_Tat_051_F","Slots":[1],"Price":1750,"Donate":0},
	"47": {"Id":47,"Name":"Sinner","Dictionary":"mpsmuggler_overlays","MaleHash":"MP_Smuggler_Tattoo_011_M","FemaleHash":"MP_Smuggler_Tattoo_011_F","Slots":[1],"Price":1750,"Donate":0},
	"48": {"Id":48,"Name":"Thief","Dictionary":"mpsmuggler_overlays","MaleHash":"MP_Smuggler_Tattoo_012_M","FemaleHash":"MP_Smuggler_Tattoo_012_F","Slots":[2],"Price":1750,"Donate":0},
	"49": {"Id":49,"Name":"Stunt Skull","Dictionary":"mpstunt_overlays","MaleHash":"MP_MP_Stunt_Tat_000_M","FemaleHash":"MP_MP_Stunt_Tat_000_F","Slots":[1],"Price":1750,"Donate":0},
	"50": {"Id":50,"Name":"Scorpion","Dictionary":"mpstunt_overlays","MaleHash":"MP_MP_Stunt_Tat_004_M","FemaleHash":"MP_MP_Stunt_Tat_004_F","Slots":[5],"Price":1750,"Donate":0},
	"51": {"Id":51,"Name":"Toxic Spider","Dictionary":"mpstunt_overlays","MaleHash":"MP_MP_Stunt_Tat_006_M","FemaleHash":"MP_MP_Stunt_Tat_006_F","Slots":[2],"Price":1750,"Donate":0},
	"52": {"Id":52,"Name":"Bat Wheel","Dictionary":"mpstunt_overlays","MaleHash":"MP_MP_Stunt_Tat_017_M","FemaleHash":"MP_MP_Stunt_Tat_017_F","Slots":[2],"Price":1750,"Donate":0},
	"53": {"Id":53,"Name":"Flaming Quad","Dictionary":"mpstunt_overlays","MaleHash":"MP_MP_Stunt_Tat_042_M","FemaleHash":"MP_MP_Stunt_Tat_042_F","Slots":[2],"Price":1750,"Donate":0}
}