{
  "FireworkPrices": [
    300,
    600,
    1500,
    2500
  ],
  "InstrumentPrices": [
    5000,
    2500,
    5000,
    15000
  ],
  "FurtinurePrices": [
    15000,
    15000,
    15000,
    75000,
    5000,
    5000,
    5000,
    5000,
    5000,
    100000,
    100000,
    100000,
    2500,
    2500,
    2500,
    2500,
    2500,
    2500,
    5000,
    5000,
    5000,
    5000,
    7500,
    5000,
    25000,
    100000,
    10000,
    100000,
    150000,
    250000,
    25000,
    500000,
    100000,
    2500,
    10000,
    3000,
    3000,
    3000,
    3000,
    3000
  ],
  "GaragesPrice": [
    8000,
    12000,
    20000,
    35000,
    50000,
    175000,
    10000,
    25000,
    50000
  ],
  "DalnoboyMoney": [
    3500,
    1000
  ],
  "CreateOrgPrice": 1500000,
  "FirstOrgPrice": 1000000,
  "SecondOrgPrice": 50000,
  "CustomsPrice": 750000,
  "StockPrice": 500000,
  "CrimeOptionsPrice": 60000,
  "UpdateTypeOrganization": 1999,
  "UpdateOrganizationLeader": 250,
  "AirdropInfoPrice": 50000,
  "AirdropOrderPrice": 250000,
  "ZapravkaMinPrice": 1,
  "ZapravkaMaxPrice": 10,
  "ClothesMinPrice": 48,
  "ClothesMaxPrice": 88,
  "TattooBarberMasksLscMinPrice": 95,
  "TattooBarberMasksLscMaxPrice": 175,
  "PistolAmmoPrice": 4,
  "ShotgunAmmoPrice": 8,
  "SMGAmmoPrice": 4,
  "RiflesAmmoPrice": 6,
  "SnniperAmmoPrice": 15,
  "PosobieNew": 500,
  "PosobieOld": 800,
  "MaxOgrableine": 3000
}