{
	"0": {"Id":0,"Variation":0,"TName":"U_FMF_0_","Textures":[0,1,2,3,4,5,6,7,8,9,10,11,12,13,14,15],"Torso":0},
	"4": {"Id":4,"Variation":4,"TName":"U_FMF_4_1","Textures":[13,14],"Torso":12},
	"5": {"Id":5,"Variation":5,"TName":"U_FMF_5_","Textures":[0,1,7,9],"Torso":4},
	"11": {"Id":11,"Variation":11,"TName":"U_FMF_11_","Textures":[0,1,2,10,11,15],"Torso":11},
	"12": {"Id":12,"Variation":12,"TName":"U_FMF_12_","Textures":[7,8,9],"Torso":12},
	"13": {"Id":13,"Variation":13,"TName":"U_FMF_13_","Textures":[0,1,2,3,4,5,6,7,8,9,10,11,12,13,14,15],"Torso":4},
	"16": {"Id":16,"Variation":16,"TName":"CLO_BBF_U_1_","Textures":[0,1,2,3,4,5,6],"Torso":4},
	"18": {"Id":18,"Variation":18,"TName":"CLO_BBF_U_3_","Textures":[0,1,2,3,4,5,6,7,8,9,10,11],"Torso":15},
	"19": {"Id":19,"Variation":19,"TName":"CLO_XMASF_U_0_","Textures":[0,1,2,3],"Torso":12},
	"22": {"Id":22,"Variation":22,"TName":"CLO_VALF_U_1_","Textures":[0,1,2,3,4],"Torso":4},
	"23": {"Id":23,"Variation":23,"TName":"CLO_VALF_U_2_","Textures":[0,1,2],"Torso":12},
	"26": {"Id":26,"Variation":26,"TName":"CLO_BUSF_U_2_","Textures":[0,1,2,3,4,5,6,7,8,9,10,11,12],"Torso":12},
	"30": {"Id":30,"Variation":30,"TName":"CLO_VALF_U_2_","Textures":[0,1,2],"Torso":2},
	"32": {"Id":32,"Variation":32,"TName":"CLO_HP_F_U_1_","Textures":[0,1,2],"Torso":4},
	"33": {"Id":33,"Variation":33,"TName":"CLO_HP_F_U_2_","Textures":[0,1,2,3,4,5,6,7,8],"Torso":4},
	"36": {"Id":36,"Variation":36,"TName":"CLO_HP_F_U_5_","Textures":[0,1,2,3,4],"Torso":4},
	"38": {"Id":38,"Variation":38,"TName":"CLO_HP_D_3","Textures":[0,1,2,3],"Torso":2},
	"40": {"Id":40,"Variation":40,"TName":"CLO_INDF_U_1_","Textures":[0,1],"Torso":2},
	"49": {"Id":49,"Variation":49,"TName":"CLO_LXF_DEC_2","Textures":[0,1],"Torso":14},
	"67": {"Id":67,"Variation":67,"TName":"CLO_LXF_U_5_","Textures":[0],"Torso":2},
	"68": {"Id":68,"Variation":68,"TName":"CLO_LXF_U_6_","Textures":[0,1,2,3,4,5,6,7,8,9,10,11,12,13,14,15,16,17,18,19],"Torso":14},
	"73": {"Id":73,"Variation":73,"TName":"CLO_S1F_U_0_","Textures":[0,1,2],"Torso":14},
	"74": {"Id":74,"Variation":74,"TName":"CLO_S1F_U_1_","Textures":[0,1,2],"Torso":4},
	"75": {"Id":75,"Variation":75,"TName":"CLO_S1F_U_2_","Textures":[0,1,2,3],"Torso":1},
	"101": {"Id":101,"Variation":101,"TName":"CLO_APF_U_19_","Textures":[0,1,2,3,4,5],"Torso":15},
	"103": {"Id":103,"Variation":103,"TName":"","Textures":[0,1,2,3,4,5],"Torso":3},
	"111": {"Id":111,"Variation":111,"TName":"CLO_V2F_U_0_","Textures":[0,1,2,3,4,5,6,7,8,9,10,11],"Torso":4},
	"117": {"Id":117,"Variation":117,"TName":"CLO_S2F_U_0_","Textures":[0,1,2],"Torso":131},
	"118": {"Id":118,"Variation":118,"TName":"CLO_S2F_U_0_","Textures":[0,1,2],"Torso":131},
	"141": {"Id":141,"Variation":141,"TName":"","Textures":[0,1,2,3,4,5],"Torso":14},
	"149": {"Id":149,"Variation":149,"TName":"CLO_STF_U_5_","Textures":[0,1,2,3,4,5,6,7,8,9,10,11,12,13,14,15],"Torso":3},
	"208": {"Id":208,"Variation":208,"TName":"CLO_IEF_U_20_","Textures":[0,1,2,3,4,5,6,7,8,9,10,11,12,13,14,15,16],"Torso":131},
	"212": {"Id":212,"Variation":212,"TName":"CLO_GRF_U_2_","Textures":[0,1,2,3,4,5,6,7,8,9,10,11,12,13,14,15,16,17,18,19,20,21,22,23],"Torso":14},
	"221": {"Id":221,"Variation":221,"TName":"CLO_GRF_U_11_","Textures":[0,1,2,3,4,5,6,7,8,9,10,11,12,13,14,15,16,17,18,19,20,21,22,23],"Torso":4},
	"222": {"Id":222,"Variation":222,"TName":"CLO_GRF_U_12_","Textures":[0,1,2,3,4,5,6,7,8,9,10,11,12,13,14,15,16,17,18,19,20,21,22,23],"Torso":4},
	"223": {"Id":223,"Variation":223,"TName":"CLO_GRF_U_13_","Textures":[0,1,2,3,4,5,6,7,8,9,10,11,12,13,14,15,16,17,18,19,20,21,22,23],"Torso":4},
	"224": {"Id":224,"Variation":224,"TName":"CLO_GRF_U_2_","Textures":[0,1,2,3,4,5,6,7,8,9,10,11,12,13,14,15,16,17,18,19,20,21,22,23],"Torso":14},
	"225": {"Id":225,"Variation":225,"TName":"CLO_GRF_U_15_","Textures":[0,1,2,3,4,5,6,7,8,9,10,11,12,13,14,15,16,17,18,19,20,21,22,23],"Torso":131},
	"226": {"Id":226,"Variation":226,"TName":"CLO_GRF_U_15_","Textures":[0,1,2,3,4,5,6,7,8,9,10,11,12,13,14,15,16,17,18,19,20,21,22,23],"Torso":131},
	"236": {"Id":236,"Variation":236,"TName":"CLO_GRF_U_26_","Textures":[0],"Torso":14},
	"245": {"Id":245,"Variation":245,"TName":"CLO_SMF_U_3_","Textures":[0,1,2,3,4,5,6,7,8,9,10,11],"Torso":14},
	"246": {"Id":246,"Variation":246,"TName":"CLO_SMF_U_4_","Textures":[0,1,2,3,4,5,6,7,8,9,10,11],"Torso":153},
	"247": {"Id":247,"Variation":247,"TName":"","Textures":[0,1,2,3,4,5,6,7,8,9,10,11,12,13,14,15,16,17,18,19,20,21,22,23,24,25],"Torso":4},
	"280": {"Id":280,"Variation":280,"TName":"CLO_BHF_U_16_","Textures":[0,1,2,3,4,5,6,7,8,9,10,11,12,13,14,15,16,17,18,19,20],"Torso":14},
	"281": {"Id":281,"Variation":281,"TName":"CLO_BHF_U_16_","Textures":[0,1,2,3,4,5,6,7,8,9,10,11,12,13,14,15,16,17,18,19,20],"Torso":14},
	"283": {"Id":283,"Variation":283,"TName":"CLO_BHF_U_19_","Textures":[0,1,2,3,4,5,6,7,8,9,10,11],"Torso":12},
	"284": {"Id":284,"Variation":284,"TName":"CLO_BHF_U_20_","Textures":[0,1,2,3,4,5,6,7,8,9,10,11],"Torso":4},
	"286": {"Id":286,"Variation":286,"TName":"CLO_AWF_U_1_","Textures":[0,1,2,3,4,5,6,7,8,9,10,11,12,13,14,15,16,17,18,19,20,21],"Torso":14},
	"421": {"Id":421,"Variation":377,"TName":"","Textures":[0,1,2,3,4,5],"Torso":14},
	"506": {"Id":506,"Variation":758,"TName":"","Textures":[0],"Torso":14}
}